siogeen/base/IoddUtility.cp313-win_amd64.pyd
siogeen/base/JSON_for_IO-Link.yaml
siogeen/base/_IoddDrv.cp313-win_amd64.pyd
siogeen/base/_IoddDrvBase.cp313-win_amd64.pyd
siogeen/base/_IoddSimDrv.cp313-win_amd64.pyd
siogeen/base/__init__.py
ioddcombase-1.9.0.dist-info/METADATA
ioddcombase-1.9.0.dist-info/WHEEL
ioddcombase-1.9.0.dist-info/top_level.txt
ioddcombase-1.9.0.dist-info/RECORD
