Metadata-Version: 2.4
Name: ioddcombase
Version: 1.9.0
Summary: IoddCom base
Home-page: https://siogeen.com
Author: Reimund Renner
Author-email: reimund@siogeen.com
License: proprietary and confidential
Project-URL: Documentation, https://siogeen.com/doc/
Project-URL: Help Desk, https://siogeen.com/helpdesk/
Project-URL: Knowledge Base, https://siogeen.com/helpdesk/knowledgebase
Project-URL: News, https://news.siogeen.com/
Keywords: IO-Link,IODD,development,test,production
Classifier: Development Status :: 5 - Production/Stable
Classifier: Intended Audience :: Developers
Classifier: Intended Audience :: Manufacturing
Classifier: Intended Audience :: Science/Research
Classifier: Intended Audience :: Customer Service
Classifier: Topic :: Software Development :: Embedded Systems
Classifier: Topic :: Software Development :: Quality Assurance
Classifier: Topic :: Software Development :: Testing
Classifier: Operating System :: Microsoft :: Windows
Classifier: Operating System :: POSIX :: Linux
Classifier: Operating System :: MacOS :: MacOS X
Classifier: License :: Other/Proprietary License
Classifier: Programming Language :: Python :: 3.9
Classifier: Programming Language :: Python :: 3.10
Classifier: Programming Language :: Python :: 3.11
Classifier: Programming Language :: Python :: 3.12
Classifier: Programming Language :: Python :: 3.13
Classifier: Programming Language :: Python :: 3.14
Requires-Python: >=3.9
Requires-Dist: bitstring>=4.1.0
Requires-Dist: psutil>=3.0.0
Requires-Dist: urllib3>=2.0.0
Requires-Dist: pyserial>=3.5
Requires-Dist: prettytable>=3.9.0
Requires-Dist: getmac>=0.9.5
Requires-Dist: isodate>=0.6.0
Requires-Dist: packaging>=23.2
Requires-Dist: PyYAML>=6.0.1
Requires-Dist: icmplib>=3.0.4
Requires-Dist: case-insensitive-dictionary>=0.2.1
Requires-Dist: cryptography>=3.4.6
Dynamic: author
Dynamic: author-email
Dynamic: classifier
Dynamic: description
Dynamic: description-content-type
Dynamic: home-page
Dynamic: keywords
Dynamic: license
Dynamic: project-url
Dynamic: requires-dist
Dynamic: requires-python
Dynamic: summary
